txl_widgets/__init__.py
txl_widgets/main.py
txl_widgets-0.3.6.dist-info/METADATA
txl_widgets-0.3.6.dist-info/WHEEL
txl_widgets-0.3.6.dist-info/entry_points.txt
txl_widgets-0.3.6.dist-info/licenses/LICENSE.txt
txl_widgets-0.3.6.dist-info/RECORD
